{
    "nombre": "Marcos",
    "edad": -14.5,
    "elementos":{
        "titulo": "Elemento 1",
        "completo": true,
        "habilidades":[
            {
                "id": 0,
                "fecha": "12/12/2020"
            },
            {
                "id": 0,
                "fecha": "12/12/2020"
            },
            {
                "id": 0,
                "fecha": "12/12/2020"
            }
        ],
        "lenguajes":{
            "lenguage01": {
                "nombre": "Javascript"
            }
        }
    }
}